Hencoder/__init__.py
test/__init__.py
test/test_basic.py
Hencoder-1.0.0.dist-info/LICENSE.txt
Hencoder-1.0.0.dist-info/METADATA
Hencoder-1.0.0.dist-info/WHEEL
Hencoder-1.0.0.dist-info/top_level.txt
Hencoder-1.0.0.dist-info/RECORD
