Metadata-Version: 2.1
Name: Hencoder
Version: 1.0.0
Summary: An text encoder based on Hauffman Encoding.
Home-page: https://github.com/Akashtyagi08/Hencoder
Author: Akash Tyagi
Author-email: akashtyagi.ta@gmail.com
License: MIT
Keywords: Hauffman,encoder,decoder,Encoding,decoding
Platform: UNKNOWN
Classifier: Programming Language :: Python :: 3
Classifier: License :: OSI Approved :: MIT License
Classifier: Operating System :: OS Independent
Requires-Python: >=3.0
